LICENSE
MANIFEST.in
README.md
setup.py
rnupythontools/__init__.py
rnupythontools/github_api.py
rnupythontools.egg-info/PKG-INFO
rnupythontools.egg-info/SOURCES.txt
rnupythontools.egg-info/dependency_links.txt
rnupythontools.egg-info/not-zip-safe
rnupythontools.egg-info/requires.txt
rnupythontools.egg-info/top_level.txt